{
  "javaparams": [
    {
      "name": "-DCLOUD_LAUNCH_CONFIG",
      "value": "improbable.launcher.AutomaticWorkerStartup"
    }
  ],

  "flagz": [
    {
      "name": "entity_activator",
      "value": "improbable.gsim.papi.NoOpEntityActivator"
    },
    {
      "name": "game_world_edge_length",
      "value": "16000"
    },
    {
      "name": "scaling_advisor_num_entities_per_worker",
      "value": "600"
    },
    {
      "name": "loadbalancer_enable",
      "value": "true"
    }
  ],

  "worker_flagz": [
    {
      "worker_type": "gsim",
      "flagz": [
        {
          "name": "bot_spawn_number",
          "value": "700"
        },
        {
          "name": "bot_spawn_range",
          "value": "600"
        }
      ]
    }
  ]
}
